tint/__init__.py
tint/__version__.py
tint/attr/__init__.py
tint/attr/augmented_occlusion.py
tint/attr/bayes.py
tint/attr/discretised_ig.py
tint/attr/dynamic_masks.py
tint/attr/extremal_mask.py
tint/attr/feature_ablation.py
tint/attr/fit.py
tint/attr/geodesic_ig.py
tint/attr/lof.py
tint/attr/non_linearities_tunnel.py
tint/attr/occlusion.py
tint/attr/retain.py
tint/attr/seq_ig.py
tint/attr/temporal_augmented_occlusion.py
tint/attr/temporal_ig.py
tint/attr/temporal_occlusion.py
tint/attr/time_forward_tunnel.py
tint/attr/models/__init__.py
tint/attr/models/bayes_linear.py
tint/attr/models/extremal_mask.py
tint/attr/models/joint_features_generator.py
tint/attr/models/mask.py
tint/attr/models/path_generator.py
tint/attr/models/retain.py
tint/data/.gitignore
tint/datasets/__init__.py
tint/datasets/arma.py
tint/datasets/biobank.py
tint/datasets/dataset.py
tint/datasets/hawkes.py
tint/datasets/hmm.py
tint/datasets/mimic3.py
tint/datasets/utils/__init__.py
tint/datasets/utils/fasttext.py
tint/datasets/utils/labels.json
tint/datasets/utils/labels.py
tint/datasets/utils/read_3_2.json
tint/metrics/__init__.py
tint/metrics/accuracy.py
tint/metrics/base.py
tint/metrics/comprehensiveness.py
tint/metrics/cross_entropy.py
tint/metrics/lipschitz_max.py
tint/metrics/log_odds.py
tint/metrics/mae.py
tint/metrics/mse.py
tint/metrics/sufficiency.py
tint/metrics/weights/__init__.py
tint/metrics/weights/lime_weights.py
tint/metrics/weights/lof_weights.py
tint/metrics/white_box/__init__.py
tint/metrics/white_box/aup.py
tint/metrics/white_box/auprc.py
tint/metrics/white_box/aur.py
tint/metrics/white_box/base.py
tint/metrics/white_box/entropy.py
tint/metrics/white_box/information.py
tint/metrics/white_box/mae.py
tint/metrics/white_box/mse.py
tint/metrics/white_box/rmse.py
tint/metrics/white_box/roc_auc.py
tint/models/__init__.py
tint/models/bert.py
tint/models/cnn.py
tint/models/distilbert.py
tint/models/mlp.py
tint/models/net.py
tint/models/rnn.py
tint/models/roberta.py
time_interpret-0.3.0.dist-info/WHEEL
time_interpret-0.3.0.dist-info/METADATA
time_interpret-0.3.0.dist-info/RECORD
